haptools/__init__.py
haptools/__main__.py
haptools/admix_storage.py
haptools/clump.py
haptools/data/__init__.py
haptools/data/breakpoints.py
haptools/data/covariates.py
haptools/data/data.py
haptools/data/genotypes.py
haptools/data/haplotypes.py
haptools/data/phenotypes.py
haptools/data/tr_harmonizer.py
haptools/index.py
haptools/karyogram.py
haptools/ld.py
haptools/logging.py
haptools/sim_genotype.py
haptools/sim_phenotype.py
haptools/transform.py
haptools-0.6.2.dist-info/METADATA
haptools-0.6.2.dist-info/WHEEL
haptools-0.6.2.dist-info/entry_points.txt
haptools-0.6.2.dist-info/licenses/LICENSE
haptools-0.6.2.dist-info/RECORD
