Metadata-Version: 2.4
Name: haptools
Version: 0.6.2
Summary: Ancestry and haplotype aware simulation of genotypes and phenotypes for complex trait analysis
License-Expression: MIT
License-File: LICENSE
Author: Arya Massarat
Requires-Python: >=3.7
Classifier: Programming Language :: Python :: 3
Classifier: Programming Language :: Python :: 3.7
Classifier: Programming Language :: Python :: 3.8
Classifier: Programming Language :: Python :: 3.9
Classifier: Programming Language :: Python :: 3.10
Classifier: Programming Language :: Python :: 3.11
Classifier: Programming Language :: Python :: 3.12
Classifier: Programming Language :: Python :: 3.13
Classifier: Programming Language :: Python :: 3.14
Requires-Dist: click (>=8.0.3)
Requires-Dist: cyvcf2 (>=0.30.14)
Requires-Dist: matplotlib (>=3.5.1)
Requires-Dist: numpy (>=1.21.3)
Requires-Dist: pgenlib (>=0.90.1)
Requires-Dist: pysam (>=0.19.0)
Project-URL: Documentation, https://haptools.readthedocs.io
Project-URL: Homepage, https://github.com/cast-genomics/haptools
Project-URL: Repository, https://github.com/cast-genomics/haptools
Project-URL: changelog, https://github.com/CAST-genomics/haptools/blob/main/CHANGELOG.md
